aslack/__init__.py
aslack/core.py
aslack/slack_api.py
aslack/utils.py
aslack/slack_bot/__init__.py
aslack/slack_bot/bot.py
aslack/slack_bot/handler.py
aslack-0.11.0.dist-info/top_level.txt
aslack-0.11.0.dist-info/METADATA
aslack-0.11.0.dist-info/DESCRIPTION.rst
aslack-0.11.0.dist-info/metadata.json
aslack-0.11.0.dist-info/WHEEL
aslack-0.11.0.dist-info/RECORD
