Metadata-Version: 2.0
Name: aslack
Version: 0.11.0
Summary: Asynchronous Slack API integration.
Home-page: http://github.com/textbook/aslack/
Author: Jonathan Sharpe
Author-email: mail@jonrshar.pe
License: License :: OSI Approved :: ISC License (ISCL)
Platform: any
Classifier: Development Status :: 3 - Alpha
Classifier: Intended Audience :: Developers
Classifier: Natural Language :: English
Classifier: Operating System :: OS Independent
Classifier: Programming Language :: Python :: 3.5
Classifier: Programming Language :: Python :: 3 :: Only
Classifier: Topic :: Communications :: Chat
Requires-Dist: aiohttp (>=0.15.0,<0.21)
Provides-Extra: examples
Requires-Dist: atmdb (>=0.1.3); extra == 'examples'
